LICENSE
MANIFEST.in
NOTICE
README.rst
setup.cfg
setup.py
docs/Makefile
docs/commands.rst
docs/conf.py
docs/contributing.rst
docs/getting_started.rst
docs/index.rst
docs/_static/kafka.svg
docs/tools/exceptions.rst
docs/tools/index.rst
docs/tools/modules.rst
docs/tools/utilities.rst
docs/tools/assigner/arguments.rst
docs/tools/assigner/batcher.rst
docs/tools/assigner/index.rst
docs/tools/assigner/actions/balance.rst
docs/tools/assigner/actions/clone.rst
docs/tools/assigner/actions/elect.rst
docs/tools/assigner/actions/remove.rst
docs/tools/assigner/actions/reorder.rst
docs/tools/assigner/actions/setrf.rst
docs/tools/assigner/actions/trim.rst
docs/tools/assigner/actions/balancemodules/count.rst
docs/tools/assigner/actions/balancemodules/even.rst
docs/tools/assigner/actions/balancemodules/leader.rst
docs/tools/assigner/actions/balancemodules/rackaware.rst
docs/tools/assigner/actions/balancemodules/size.rst
docs/tools/assigner/models/reassignment.rst
docs/tools/assigner/models/replica_election.rst
docs/tools/assigner/sizers/ssh.rst
docs/tools/models/broker.rst
docs/tools/models/cluster.rst
docs/tools/models/partition.rst
docs/tools/models/topic.rst
docs/tools/protocol/arguments.rst
docs/tools/protocol/errors.rst
docs/tools/protocol/help.rst
docs/tools/protocol/index.rst
docs/tools/protocol/requests/api_versions_v0.rst
docs/tools/protocol/requests/controlled_shutdown_v1.rst
docs/tools/protocol/requests/create_topics_v0.rst
docs/tools/protocol/requests/delete_topics_v0.rst
docs/tools/protocol/requests/describe_groups_v0.rst
docs/tools/protocol/requests/group_coordinator_v0.rst
docs/tools/protocol/requests/heartbeat_v0.rst
docs/tools/protocol/requests/join_group_v0.rst
docs/tools/protocol/requests/leader_and_isr_v0.rst
docs/tools/protocol/requests/leave_group_v0.rst
docs/tools/protocol/requests/list_groups_v0.rst
docs/tools/protocol/requests/list_offset_v0.rst
docs/tools/protocol/requests/offset_commit_v0.rst
docs/tools/protocol/requests/offset_commit_v1.rst
kafka_tools.egg-info/PKG-INFO
kafka_tools.egg-info/SOURCES.txt
kafka_tools.egg-info/dependency_links.txt
kafka_tools.egg-info/entry_points.txt
kafka_tools.egg-info/requires.txt
kafka_tools.egg-info/top_level.txt
