Metadata-Version: 1.1
Name: kafka-tools
Version: 0.1.9
Summary: A collection of tools and scripts for working with Apache Kafka
Home-page: https://github.com/linkedin/kafka-tools
Author: Todd Palino
Author-email: tpalino@linkedin.com
License: Apache 2.0
Keywords: kafka tools admin
Platform: UNKNOWN
Classifier: Development Status :: 3 - Alpha
Classifier: Intended Audience :: System Administrators
Classifier: Topic :: Utilities
Classifier: License :: OSI Approved :: Apache Software License
Classifier: Programming Language :: Python :: 2
Classifier: Programming Language :: Python :: 2.7
Classifier: Programming Language :: Python :: 3
Classifier: Programming Language :: Python :: 3.5
